{
  "id": "/Users/tejas/Sites/LAB/tejjer/apps/solid/src/components/Sidebar.tsx",
  "deps": [],
  "plugins": [
    "vite:load-fallback",
    "solid"
  ],
  "transforms": [
    {
      "name": "vite:load-fallback",
      "result": "import { css } from \"solid-styled-components\";\n\nimport Avatar from \"./Avatar\";\nimport Button from \"./Button\";\nimport Logo from \"./Logo\";\nimport MenuItem from \"./MenuItem\";\n\nfunction Sidebar(props) {\n  return (\n    <div class=\"relative\">\n      <div class=\"flex-col hidden h-screen overflow-auto md:flex md:top-0 md:fixed\">\n        <div class=\"px-4 py-8\">\n          <Logo></Logo>\n        </div>\n        <nav>\n          <ul>\n            <li>\n              <MenuItem>\n                <button\n                  class=\"w-full text-left\"\n                  onClick={(event) => alert(\"Not yet implemented!\")}\n                >\n                  Home\n                </button>\n              </MenuItem>\n            </li>\n            <li>\n              <MenuItem>\n                <button\n                  class=\"w-full text-left\"\n                  onClick={(event) => alert(\"Not yet implemented!\")}\n                >\n                  Explore\n                </button>\n              </MenuItem>\n            </li>\n            <li>\n              <MenuItem>\n                <button\n                  class=\"w-full text-left\"\n                  onClick={(event) => alert(\"Not yet implemented!\")}\n                >\n                  Communities\n                </button>\n              </MenuItem>\n            </li>\n            <li>\n              <MenuItem>\n                <button\n                  class=\"w-full text-left\"\n                  onClick={(event) => alert(\"Not yet implemented!\")}\n                >\n                  Notifications\n                </button>\n              </MenuItem>\n            </li>\n            <li>\n              <MenuItem>\n                <button\n                  class=\"w-full text-left\"\n                  onClick={(event) => alert(\"Not yet implemented!\")}\n                >\n                  Messages\n                </button>\n              </MenuItem>\n            </li>\n            <li>\n              <MenuItem>\n                <button\n                  class=\"w-full text-left\"\n                  onClick={(event) => alert(\"Not yet implemented!\")}\n                >\n                  Bookmarks\n                </button>\n              </MenuItem>\n            </li>\n            <li>\n              <MenuItem>\n                <button\n                  class=\"w-full text-left\"\n                  onClick={(event) => alert(\"Not yet implemented!\")}\n                >\n                  Profile\n                </button>\n              </MenuItem>\n            </li>\n            <li>\n              <MenuItem>\n                <button\n                  class=\"w-full text-left\"\n                  onClick={(event) => alert(\"Not yet implemented!\")}\n                >\n                  More\n                </button>\n              </MenuItem>\n            </li>\n            <li>\n              <div class=\"p-4\">\n                <Button\n                  onClick={(event) =>\n                    document.querySelector(\"#composer\").focus()\n                  }\n                  fullWidth={true}\n                >\n                  Tweet\n                </Button>\n              </div>\n            </li>\n          </ul>\n        </nav>\n        <div class=\"flex items-center w-full gap-4 p-4 mt-auto text-sm\">\n          <div>\n            <Avatar\n              alt={props.me.name}\n              url={props.me.profile_image_url}\n            ></Avatar>\n          </div>\n          <div>\n            <div class=\"font-bold\">{props.me.name}</div>\n            <div class=\"text-gray-400\">@{props.me.username}</div>\n          </div>\n          <div class=\"ml-auto\">...</div>\n        </div>\n      </div>\n    </div>\n  );\n}\n\nexport default Sidebar;\n",
      "start": 1669937513953,
      "end": 1669937514010
    },
    {
      "name": "solid",
      "result": "import { ssr as _$ssr } from \"solid-js/web\";\nimport { escape as _$escape } from \"solid-js/web\";\nimport { createComponent as _$createComponent } from \"solid-js/web\";\nimport { ssrHydrationKey as _$ssrHydrationKey } from \"solid-js/web\";\nconst _tmpl$ = [\"<button\", \" class=\\\"w-full text-left\\\">Home</button>\"],\n  _tmpl$2 = [\"<button\", \" class=\\\"w-full text-left\\\">Explore</button>\"],\n  _tmpl$3 = [\"<button\", \" class=\\\"w-full text-left\\\">Communities</button>\"],\n  _tmpl$4 = [\"<button\", \" class=\\\"w-full text-left\\\">Notifications</button>\"],\n  _tmpl$5 = [\"<button\", \" class=\\\"w-full text-left\\\">Messages</button>\"],\n  _tmpl$6 = [\"<button\", \" class=\\\"w-full text-left\\\">Bookmarks</button>\"],\n  _tmpl$7 = [\"<button\", \" class=\\\"w-full text-left\\\">Profile</button>\"],\n  _tmpl$8 = [\"<button\", \" class=\\\"w-full text-left\\\">More</button>\"],\n  _tmpl$9 = [\"<div\", \" class=\\\"relative\\\"><div class=\\\"flex-col hidden h-screen overflow-auto md:flex md:top-0 md:fixed\\\"><div class=\\\"px-4 py-8\\\">\", \"</div><nav><ul><li>\", \"</li><li>\", \"</li><li>\", \"</li><li>\", \"</li><li>\", \"</li><li>\", \"</li><li>\", \"</li><li>\", \"</li><li><div class=\\\"p-4\\\">\", \"</div></li></ul></nav><div class=\\\"flex items-center w-full gap-4 p-4 mt-auto text-sm\\\"><div>\", \"</div><div><div class=\\\"font-bold\\\">\", \"</div><div class=\\\"text-gray-400\\\">@<!--#-->\", \"<!--/--></div></div><div class=\\\"ml-auto\\\">...</div></div></div></div>\"];\nimport \"solid-styled-components\";\nimport Avatar from \"./Avatar\";\nimport Button from \"./Button\";\nimport Logo from \"./Logo\";\nimport MenuItem from \"./MenuItem\";\nfunction Sidebar(props) {\n  return _$ssr(_tmpl$9, _$ssrHydrationKey(), _$escape(_$createComponent(Logo, {})), _$escape(_$createComponent(MenuItem, {\n    get children() {\n      return _$ssr(_tmpl$, _$ssrHydrationKey());\n    }\n  })), _$escape(_$createComponent(MenuItem, {\n    get children() {\n      return _$ssr(_tmpl$2, _$ssrHydrationKey());\n    }\n  })), _$escape(_$createComponent(MenuItem, {\n    get children() {\n      return _$ssr(_tmpl$3, _$ssrHydrationKey());\n    }\n  })), _$escape(_$createComponent(MenuItem, {\n    get children() {\n      return _$ssr(_tmpl$4, _$ssrHydrationKey());\n    }\n  })), _$escape(_$createComponent(MenuItem, {\n    get children() {\n      return _$ssr(_tmpl$5, _$ssrHydrationKey());\n    }\n  })), _$escape(_$createComponent(MenuItem, {\n    get children() {\n      return _$ssr(_tmpl$6, _$ssrHydrationKey());\n    }\n  })), _$escape(_$createComponent(MenuItem, {\n    get children() {\n      return _$ssr(_tmpl$7, _$ssrHydrationKey());\n    }\n  })), _$escape(_$createComponent(MenuItem, {\n    get children() {\n      return _$ssr(_tmpl$8, _$ssrHydrationKey());\n    }\n  })), _$escape(_$createComponent(Button, {\n    onClick: event => document.querySelector(\"#composer\").focus(),\n    fullWidth: true,\n    children: \"Tweet\"\n  })), _$escape(_$createComponent(Avatar, {\n    get alt() {\n      return props.me.name;\n    },\n    get url() {\n      return props.me.profile_image_url;\n    }\n  })), _$escape(props.me.name), _$escape(props.me.username));\n}\nexport default Sidebar;",
      "start": 1669937514010,
      "end": 1669937514017
    }
  ],
  "virtual": false
}